{
  "status": 0,
  "message": "success",
  "data": {
    "id": 74,
    "title": "计划列表",
    "method": "get",
    "path": "/rb/campaign",
    "namespace": "联通",
    "description": null,
    "delay": null,
    "schema": "function({_req}) {\n  const pageIndex = Number(_req.query.pageIndex || 0);\n  const pageSize = Number(_req.query.pageSize || 10);\n  const current = pageIndex * pageSize;\n  return {\n    total: 500,\n    count: 500,\n    rows: new Array(pageSize).fill(0).map((_, index) => {\n      const campaign_status = Math.floor(Math.random() * 4) + 1;\n      return {\n        \"contract_item_id\": 41383 + current,\n        \"contract_no\": \"KABP_1C83ABC871A216FB44036468A4C9470D\" + campaign_status,\n        \"contract_name\": \"\",\n        \"resource_name\": \"微博客户端开机首刷\" + campaign_status,\n        \"creative_id\": 16699 + campaign_status,\n        \"creative_name\": \"崔萌萌__20230726\" + campaign_status,\n        \"resource_details\": \"微博客户端开机首刷[大出框,Maxvision,优选触达,外链,不限,不限,静态按钮]CPD\",\n        \"batch_uid\": \"KABP_1C83ABC871A216FB44036468A4C9470D_NO20230726_180625\",\n        \"app\": \"微博主端\",\n        \"scheduled_days\": 1,\n        \"start_date\": \"2023-08-31\",\n        \"end_date\": \"2023-08-31\",\n        \"is_rush\": 0,\n        \"position_name\": \"微博客户端开机首刷\",\n        \"product_line\": 2,\n        \"sales_type\": 1,\n        \"sales_type_name\": \"首刷CPD\",\n        \"media_type\": 1516,\n        \"media_type_name\": \"Maxvision\",\n        \"interaction_type\": 1561,\n        \"interaction_type_name\": \"优选触达-静态按钮\",\n        \"increment_type_name\": \"大出框\",\n        \"increment_type\": [\n          1577\n        ],\n        \"condition_setting\": \"平台,性别\",\n        \"suit_name\": null,\n        \"customer_name\": \"\",\n        \"source_name\": \"KABP\",\n        \"company_name\": \"\",\n        \"customer_id\": 0,\n        \"sales_name\": null,\n        \"media_name\": \"崔萌萌\",\n        \"media_num\": \"213451\",\n        \"ae_name\": \"罗亮\",\n        \"ae_num\": \"14345\",\n        \"creative_status\": 2,\n        \"target_impression\": campaign_status * 10,\n        \"current_impression\": 60,\n        \"progress_desc\": null,\n        \"campaign_status\": campaign_status,\n        \"campaign_id\": 26404267,\n        \"campaign_name\": \"崔萌萌__20230726\" + campaign_status,\n        \"monitor_type_name\": \"无\",\n        \"is_rpm\": \"否\",\n        \"pdps\": \"PDPS000000066785\",\n        \"delivery_type\": 1,\n        \"biz_scene\": \"BOOT\",\n        \"wax_total_count\": null,\n        \"wax_pass_count\": null,\n        \"wax_wait_audit_count\": null,\n        \"wax_reject_count\": null,\n        \"reject_reason\": null,\n        \"dsp_id\": 0\n      };\n    })\n  }\n}",
    "createdBy": "admin",
    "createdAt": "2024-10-03T22:11:25.000Z",
    "updatedAt": "2024-10-03T22:34:50.000Z"
  }
}